fullAdder.v
//*************************************************************************
// Author(s): Shane Duffy
// Creation Date: Friday 5 February 2025
// Class: ECE 363 - Design of Digital Systems
// Lab this program is associated with: Lab 1
// Lab due date: Monday 10 February 2025 @ 12:00AM
//
// Purpose of program: Implement single full adder unit.
//
// Additional files needed: N/A
//
// Date of last modification: 6 February 2025 @ 22:48
//*************************************************************************

//******************
//
// Start of Module
//    full_ADD
//
//******************

module full_ADD ( 		// defining data inputs and outputs
	input wire a, 		// input data
	input wire b,
	input wire carryIn,
	output sum,
	output carry
);

    wire w1, w2, w3, w4;	// connective wires

    xor(w1, a, b);		// finding the sum from a, b, and our carry in	
    xor(sum, w1, carryIn);	// xor used in lew of AND, OR, & NOT for clarity

    and(w2, a, b);		//parameters needed to obtain carry out
    and(w3, b, carryIn);
    and(w4, carryIn, a);	

    or(carry, w2, w3, w4);	//getting our carry out
    
endmodule

Lab1/ripple2Adder.v
//*************************************************************************
// Author(s): Shane Duffy
// Creation Date: Friday 8 February 2025
// Class: ECE 363 - Design of Digital Systems
// Lab this program is associated with: Lab 1
// Lab due date: Monday 10 February 2025 @ 12:00AM
//
// Purpose of program: Implement 2 bit ripple carry adder.
//
// Additional files needed: ../fullADD/fullAdder.v
//
// Date of last modification: 10 February 2025 @ 4:48
//*************************************************************************

//******************
//
// Start of Module
//    rippleADD
//
//******************

`include "../fullADD/fullAdder.v"

module rippleADD(		//--------------------------
	input[1:0] a, b,	// var declaration
	input carryIn,		// note a,b, & sum are [1:0]
	output[1:0] sum,	//-------------------------
	output carryOut);

wire carryWithin;		// declare an internal "rippling" carry

// stage 1 and stage two of the ripple carry adder

full_ADD stage0(a[0], b[0], carryIn, sum[0], carryWithin); 
full_ADD stage1(a[1], b[1], carryWithin, sum[1], carryOut);

endmodule

Lab2/combo_lab/adder_2/ripple2Adder_testbench.sv
//*************************************************************************
// Author(s): Shane Duffy
// Creation Date: Friday 5 February 2025
// Class: ECE 363 - Design of Digital Systems
// Lab this program is associated with: Lab 1
// Lab due date: Monday 10 February 2025 @ 12:00AM
//
// Purpose of program: Test Bench for single full adder unit.
//
// Additional files needed: fullAdder.v
//
// Date of last modification: 9 February 2025 @ 17:48
//*************************************************************************

`timescale 1ns/100ps

module rippleADD_tb;
	reg [1:0] a, b;			//---------------------------
	reg carryIn;			// Definition of vars &
	wire [1:0] sum;			// DUT pipelining
	wire carryOut;			// *note 2 bit a,b, and sum
							//--------------------------
	rippleADD dut(  .a(a),
			.b(b),
			.carryIn(carryIn),
			.carryOut(carryOut),
			.sum(sum)
		     );

initial begin				//init a, b, and cin
	a = 2'b00;			//as 00, 00, and 0
	b = 2'b00;
	carryIn = 0;
end

always begin				//queue the truth table style of test case iteration
	#5 carryIn = 1;
	#5 carryIn = 0; a = 2'b01;
	#5 carryIn = 1; 
	#5 carryIn = 0; a = 2'b10;
	#5 carryIn = 1; 
	#5 carryIn = 0; a = 2'b11;
	#5 carryIn = 1; 
	#5 carryIn = 0; a = 2'b00; b = 2'b01; 
	#5 carryIn = 1;
	#5 carryIn = 0; a = 2'b01;
	#5 carryIn = 1; 
	#5 carryIn = 0; a = 2'b10;
	#5 carryIn = 1; 
	#5 carryIn = 0; a = 2'b11;
	#5 carryIn = 1; 
	#5 carryIn = 0; a = 2'b00; b = 2'b10; 
	#5 carryIn = 1;
	#5 carryIn = 0; a = 2'b01;
	#5 carryIn = 1; 
	#5 carryIn = 0; a = 2'b10;
	#5 carryIn = 1; 
	#5 carryIn = 0; a = 2'b11;
	#5 carryIn = 1; 
	#5 carryIn = 0; a = 2'b00; b = 2'b11; 
	#5 carryIn = 1;
	#5 carryIn = 0; a = 2'b01;
	#5 carryIn = 1; 
	#5 carryIn = 0; a = 2'b10;
	#5 carryIn = 1; 
	#5 carryIn = 0; a = 2'b11;
	#5 carryIn = 1; 
end

initial begin				//----------------------
	$dumpfile("rippleADDTest.vcd");	// Dumpfile and TT
	$dumpvars;			// output boilerplate
end					//
					//---------------------
initial begin
	$display("\ta,\tb,\tcIn,\tcout,\tsum");
	$monitor ("\t%02b\t%02b\t%0b\t%0b\t%02b", a, b, carryIn, carryOut, sum);
end

initial #160 $finish;	// run for 160ms, then finish
endmodule

rippleADDTest.vcd
$date
	Mon Feb 10 04:53:07 2025
$end

$version
	Synopsys VCS version W-2024.09-SP1_Full64
$end

$timescale
	100ps
$end

$comment Csum: 1 ccfd28f5afcd309d $end


$scope module rippleADD_tb $end
$var reg 2 ! a [1:0] $end
$var reg 2 " b [1:0] $end
$var reg 1 # carryIn $end
$var wire 2 $ sum [1:0] $end
$var wire 1 % carryOut $end

$scope module dut $end
$var wire 2 & a [1:0] $end
$var wire 2 ' b [1:0] $end
$var wire 1 ( carryIn $end
$var wire 2 $ sum [1:0] $end
$var wire 1 % carryOut $end
$var wire 1 ) carryWithin $end

$scope module stage0 $end
$var wire 1 * a $end
$var wire 1 + b $end
$var wire 1 ( carryIn $end
$var wire 1 , sum $end
$var wire 1 ) carry $end
$var wire 1 - w1 $end
$var wire 1 . w2 $end
$var wire 1 / w3 $end
$var wire 1 0 w4 $end
$upscope $end


$scope module stage1 $end
$var wire 1 1 a $end
$var wire 1 2 b $end
$var wire 1 ) carryIn $end
$var wire 1 3 sum $end
$var wire 1 % carry $end
$var wire 1 4 w1 $end
$var wire 1 5 w2 $end
$var wire 1 6 w3 $end
$var wire 1 7 w4 $end
$upscope $end

$upscope $end

$upscope $end

$enddefinitions $end

#0
$dumpvars
0#
x,
x3
x*
x1
x+
x2
b00 !
b00 "
b00 &
b00 '
b00 $
0)
0%
0-
0.
04
05
0(
0/
00
06
07
$end
0,
03
0*
01
0+
02
#50
1#
1(
b01 $
1,
#100
0#
0(
b00 $
0,
b01 !
b01 &
1*
1-
b01 $
1,
#150
1#
1(
b00 $
0,
10
1)
b10 $
13
#200
0#
0(
b11 $
1,
00
0)
b01 $
03
b10 !
b10 &
0*
11
14
b11 $
13
0-
b10 $
0,
#250
1#
1(
b11 $
1,
#300
0#
0(
b10 $
0,
b11 !
b11 &
1*
1-
b11 $
1,
#350
1#
1(
b10 $
0,
10
1)
b00 $
03
17
1%
#400
0#
0(
b01 $
1,
00
0)
b11 $
13
07
0%
b00 !
b00 &
0*
01
04
b01 $
03
0-
b00 $
0,
b01 "
b01 '
1+
1-
b01 $
1,
#450
1#
1(
b00 $
0,
1/
1)
b10 $
13
#500
0#
0(
b11 $
1,
0/
0)
b01 $
03
b01 !
b01 &
1*
1.
1)
b11 $
13
0-
b10 $
0,
#550
1#
1(
b11 $
1,
1/
10
#600
0#
0(
b10 $
0,
0/
00
b10 !
b10 &
0*
11
17
1%
14
b00 $
03
0.
0)
b10 $
13
07
0%
1-
b11 $
1,
#650
1#
1(
b10 $
0,
1/
1)
b00 $
03
17
1%
#700
0#
0(
b01 $
1,
0/
0)
b11 $
13
07
0%
b11 !
b11 &
1*
1.
1)
b01 $
03
17
1%
0-
b00 $
0,
#750
1#
1(
b01 $
1,
1/
10
#800
0#
0(
b00 $
0,
0/
00
b00 !
b00 &
0*
01
07
0%
04
b10 $
13
0.
0)
b00 $
03
1-
b01 $
1,
b10 "
b10 '
0+
12
14
b11 $
13
0-
b10 $
0,
#850
1#
1(
b11 $
1,
#900
0#
0(
b10 $
0,
b01 !
b01 &
1*
1-
b11 $
1,
#950
1#
1(
b10 $
0,
10
1)
b00 $
03
16
1%
#1000
0#
0(
b01 $
1,
00
0)
b11 $
13
06
0%
b10 !
b10 &
0*
11
15
1%
04
b01 $
03
0-
b00 $
0,
#1050
1#
1(
b01 $
1,
#1100
0#
0(
b00 $
0,
b11 !
b11 &
1*
1-
b01 $
1,
#1150
1#
1(
b00 $
0,
10
1)
b10 $
13
16
17
#1200
0#
0(
b11 $
1,
00
0)
b01 $
03
06
07
b00 !
b00 &
0*
01
05
0%
14
b11 $
13
0-
b10 $
0,
b11 "
b11 '
1+
1-
b11 $
1,
#1250
1#
1(
b10 $
0,
1/
1)
b00 $
03
16
1%
#1300
0#
0(
b01 $
1,
0/
0)
b11 $
13
06
0%
b01 !
b01 &
1*
1.
1)
b01 $
03
16
1%
0-
b00 $
0,
#1350
1#
1(
b01 $
1,
1/
10
#1400
0#
0(
b00 $
0,
0/
00
b10 !
b10 &
0*
11
17
15
04
b10 $
13
0.
0)
b00 $
03
06
07
1-
b01 $
1,
#1450
1#
1(
b00 $
0,
1/
1)
b10 $
13
16
17
#1500
0#
0(
b11 $
1,
0/
0)
b01 $
03
06
07
b11 !
b11 &
1*
1.
1)
b11 $
13
16
17
0-
b10 $
0,
#1550
1#
1(
b11 $
1,
1/
10
